calculator/__init__.py
calculator/main.py
calculator/operations.py
pythonpackages_rgoyal-1.0.0.dist-info/licenses/LICENSE
pythonpackages_rgoyal-1.0.0.dist-info/METADATA
pythonpackages_rgoyal-1.0.0.dist-info/WHEEL
pythonpackages_rgoyal-1.0.0.dist-info/entry_points.txt
pythonpackages_rgoyal-1.0.0.dist-info/top_level.txt
pythonpackages_rgoyal-1.0.0.dist-info/RECORD
