Metadata-Version: 2.4
Name: pythonPackages-rgoyal
Version: 1.0.0
Summary: A small example package having basic calculator functions
Author-email: Riya <author@example.com>
Project-URL: Homepage, https://github.com/example/example-package
Project-URL: Bug Tracker, https://github.com/example/example-package/issues
Classifier: Programming Language :: Python :: 3
Classifier: License :: OSI Approved :: MIT License
Classifier: Operating System :: OS Independent
Requires-Python: ==3.13
License-File: LICENSE
Requires-Dist: requests>=2.25.0
Requires-Dist: numpy>=1.19.0
Provides-Extra: dev
Requires-Dist: pytest>=6.0.0; extra == "dev"
Requires-Dist: black>=21.5b2; extra == "dev"
Dynamic: license-file
